kafka_ops_guide/__init__.py
kafka_ops_guide/main.py
kafka_ops_guide/prompts.py
kafka_ops_guide-2025.12.20185738.dist-info/METADATA
kafka_ops_guide-2025.12.20185738.dist-info/WHEEL
kafka_ops_guide-2025.12.20185738.dist-info/top_level.txt
kafka_ops_guide-2025.12.20185738.dist-info/RECORD
