Metadata-Version: 2.4
Name: kafka-ops-guide
Version: 2025.12.20185738
Summary: A new package that provides structured, reliable summaries of technical concepts related to Kafka operations, such as partition management. It takes user-provided text (e.g., a query about increasing 
Author-email: kafka-ops-guide <hi@eugene.plus>
License: MIT
Project-URL: Homepage, https://github.com/chigwell/kafka-ops-guide
Requires-Python: >=3.9
Requires-Dist: langchain-llm7>=0.0.0
Requires-Dist: llmatch-messages>=0.0.0
Requires-Dist: langchain-core>=0.3.0
